setup.py
mytheme/__init__.py
mytheme/_version.py
jupyterlab_theme_onedark-0.1.0.data/data/share/jupyter/labextensions/mytheme/package.json
jupyterlab_theme_onedark-0.1.0.data/data/share/jupyter/labextensions/mytheme/static/568.c41adb173daf8b94d96f.js
jupyterlab_theme_onedark-0.1.0.data/data/share/jupyter/labextensions/mytheme/static/remoteEntry.07e1f351c23fbc1a7c5f.js
jupyterlab_theme_onedark-0.1.0.data/data/share/jupyter/labextensions/mytheme/static/style.js
jupyterlab_theme_onedark-0.1.0.data/data/share/jupyter/labextensions/mytheme/static/third-party-licenses.json
jupyterlab_theme_onedark-0.1.0.data/data/share/jupyter/labextensions/mytheme/themes/jupyterlab-theme-onedark/index.css
jupyterlab_theme_onedark-0.1.0.data/data/share/jupyter/labextensions/mytheme/themes/jupyterlab-theme-onedark/index.js
jupyterlab_theme_onedark-0.1.0.data/data/share/jupyter/labextensions/mytheme/install.json
jupyterlab_theme_onedark-0.1.0.dist-info/METADATA
jupyterlab_theme_onedark-0.1.0.dist-info/WHEEL
jupyterlab_theme_onedark-0.1.0.dist-info/licenses/LICENSE
jupyterlab_theme_onedark-0.1.0.dist-info/RECORD
