Metadata-Version: 2.1
Name: jupyterlab-theme-onedark
Version: 0.1.0
Summary: A JupyterLab extension.
Project-URL: Homepage, https://github.com/tinaloong/jupyterlab-theme-onedark/tree/main
Project-URL: Bug Tracker, https://github.com/tinaloong/jupyterlab-theme-onedark/issues
Project-URL: Repository, https://github.com/tinaloong/jupyterlab-theme-onedark.git
Author-email: "guixia.lgx" <guixia.lgx@alibaba-inc.com>
License: BSD 3-Clause License
License-File: LICENSE
Classifier: Framework :: Jupyter
Classifier: Framework :: Jupyter :: JupyterLab
Classifier: Framework :: Jupyter :: JupyterLab :: 4
Classifier: Framework :: Jupyter :: JupyterLab :: Extensions
Classifier: Framework :: Jupyter :: JupyterLab :: Extensions :: Prebuilt
Classifier: License :: OSI Approved :: BSD License
Classifier: Programming Language :: Python
Classifier: Programming Language :: Python :: 3
Classifier: Programming Language :: Python :: 3.8
Classifier: Programming Language :: Python :: 3.9
Classifier: Programming Language :: Python :: 3.10
Classifier: Programming Language :: Python :: 3.11
Requires-Python: >=3.8
